Metadata-Version: 2.1
Name: quranbot
Version: 0.0.1
Summary: A package developed by SaudiBits to facilitate the process of making a quran bot
Author: Ahmed Alnasser
Author-email: itzzmega2005@gmail.com
License: MIT
Keywords: Quran,Bot
Classifier: Development Status :: 1 - Planning
Classifier: Intended Audience :: Developers
Classifier: Programming Language :: Python :: 3
Classifier: Operating System :: Unix
Classifier: Operating System :: MacOS :: MacOS X
Classifier: Operating System :: Microsoft :: Windows
Classifier: License :: OSI Approved :: MIT License
License-File: LICENSE.txt
